MANIFEST.in
README.rst
setup.py
django_icons_tango.egg-info/PKG-INFO
django_icons_tango.egg-info/SOURCES.txt
django_icons_tango.egg-info/dependency_links.txt
django_icons_tango.egg-info/requires.txt
django_icons_tango.egg-info/top_level.txt
icons_tango/__init__.py
icons_tango/models.py
icons_tango/static/icons/tango/AUTHORS
icons_tango/static/icons/tango/COPYING
icons_tango/static/icons/tango/ChangeLog
icons_tango/static/icons/tango/README
icons_tango/static/icons/tango/16x16/actions/address-book-new.png
icons_tango/static/icons/tango/16x16/actions/appointment-new.png
icons_tango/static/icons/tango/16x16/actions/bookmark-new.png
icons_tango/static/icons/tango/16x16/actions/contact-new.png
icons_tango/static/icons/tango/16x16/actions/document-new.png
icons_tango/static/icons/tango/16x16/actions/document-open.png
icons_tango/static/icons/tango/16x16/actions/document-print-preview.png
icons_tango/static/icons/tango/16x16/actions/document-print.png
icons_tango/static/icons/tango/16x16/actions/document-properties.png
icons_tango/static/icons/tango/16x16/actions/document-save-as.png
icons_tango/static/icons/tango/16x16/actions/document-save.png
icons_tango/static/icons/tango/16x16/actions/edit-clear.png
icons_tango/static/icons/tango/16x16/actions/edit-copy.png
icons_tango/static/icons/tango/16x16/actions/edit-cut.png
icons_tango/static/icons/tango/16x16/actions/edit-delete.png
icons_tango/static/icons/tango/16x16/actions/edit-find-replace.png
icons_tango/static/icons/tango/16x16/actions/edit-find.png
icons_tango/static/icons/tango/16x16/actions/edit-paste.png
icons_tango/static/icons/tango/16x16/actions/edit-redo.png
icons_tango/static/icons/tango/16x16/actions/edit-select-all.png
icons_tango/static/icons/tango/16x16/actions/edit-undo.png
icons_tango/static/icons/tango/16x16/actions/folder-new.png
icons_tango/static/icons/tango/16x16/actions/format-indent-less.png
icons_tango/static/icons/tango/16x16/actions/format-indent-more.png
icons_tango/static/icons/tango/16x16/actions/format-justify-center.png
icons_tango/static/icons/tango/16x16/actions/format-justify-fill.png
icons_tango/static/icons/tango/16x16/actions/format-justify-left.png
